FalconSearch/FalconSearch.py
FalconSearch/__init__.py
FalconSearch/clear.py
FalconSearch-0.0.9.dist-info/METADATA
FalconSearch-0.0.9.dist-info/WHEEL
FalconSearch-0.0.9.dist-info/top_level.txt
FalconSearch-0.0.9.dist-info/RECORD
