Metadata-Version: 2.1
Name: FalconSearch
Version: 0.0.9
Summary: FalconSearch can identify people in videos and cctv footage!
Author-email: Michael Mueller <michael.j.mueller.pro@gmail.com>
Project-URL: Homepage, https://github.com/Invizabel/FalconSearch
Project-URL: Bug Tracker, https://github.com/Invizabel/FalconSearch/issues
Classifier: Programming Language :: Python :: 3
Classifier: License :: OSI Approved :: MIT License
Classifier: Operating System :: OS Independent
Requires-Python: >=3.8
Requires-Dist: face-recognition
Requires-Dist: moviepy
Requires-Dist: opencv-python
